kanaries_track/__init__.py
kanaries_track/client.py
kanaries_track/config.py
kanaries_track/request.py
kanareis_track-0.0.1.dist-info/METADATA
kanareis_track-0.0.1.dist-info/WHEEL
kanareis_track-0.0.1.dist-info/licenses/LICENSE
kanareis_track-0.0.1.dist-info/RECORD
