Metadata-Version: 2.1
Name: kanareis_track
Version: 0.0.1
Summary: kanareis_track: track to kanareis data infra
Project-URL: homepage, https://github.com/Kanaries/kanaries-track
Project-URL: repository, https://github.com/Kanaries/kanaries-track
Author-email: kanaries <support@kanaries.net>
License-File: LICENSE
Keywords: kanareis,track
Classifier: License :: OSI Approved :: Apache Software License
Classifier: Programming Language :: Python :: 3
Requires-Python: >=3.6
Requires-Dist: backoff==2.2.1
Requires-Dist: dateutils==0.6.12
Requires-Dist: requests==2.31.0
Provides-Extra: dev
Requires-Dist: build; extra == 'dev'
Requires-Dist: pytest; extra == 'dev'
Requires-Dist: twine; extra == 'dev'
